gait-gm/__init__.py
gait-gm/data/PCA2GO.2.R
gait-gm/data/__init__.py
gait-gm/data/all_by_all_correlation.R
gait-gm/data/sPLS.R
gaitGM/__init__.py
gaitGM/keggPeaModules.py
gaitGM/data/PCA2GO.2.R
gaitGM/data/__init__.py
gaitGM/data/all_by_all_correlation.R
gaitGM/data/sPLS.R
gaitGM/data/__pycache__/__init__.cpython-37.pyc
gaitGM/data/__pycache__/__init__.cpython-39.pyc
gait_gm-21.7.22.data/scripts/add_kegg_anno_info.py
gait_gm-21.7.22.data/scripts/add_kegg_pathway_info.py
gait_gm-21.7.22.data/scripts/add_pval_flags.py
gait_gm-21.7.22.data/scripts/all_by_all_correlation.py
gait_gm-21.7.22.data/scripts/ensembl2symbol.py
gait_gm-21.7.22.data/scripts/sPLS.py
gait_gm-21.7.22.data/scripts/split_wide_dataset.py
gait_gm-21.7.22.dist-info/METADATA
gait_gm-21.7.22.dist-info/WHEEL
gait_gm-21.7.22.dist-info/top_level.txt
gait_gm-21.7.22.dist-info/RECORD
