Metadata-Version: 2.1
Name: gait-gm
Version: 21.7.22
Summary: "Modeling Metabolites as a function of gene expression"
Home-page: https://github.com/secimTools/gait-gm
Author: McIntyre Lab, Universify of Florida
Author-email: om@rc.ufl.edu
License: MIT
Keywords: modeling metabolites as a function of gene expression
Platform: any
Classifier: Development Status :: 5 - Production/Stable
Classifier: Environment :: Console
Classifier: Intended Audience :: Science/Research
Classifier: Operating System :: OS Independent
Classifier: License :: OSI Approved :: MIT License
Classifier: Programming Language :: Python :: 3
Classifier: Topic :: Scientific/Engineering
Classifier: Topic :: Scientific/Engineering :: Bio-Informatics
Requires-Python: >=3.7
Requires-Dist: biopython (>=1.70)
Requires-Dist: numpy (>=1.18.1)
Requires-Dist: pandas (>=1.0.3)
Requires-Dist: secimtools (>=21.6.3)
